qs/__init__.py
qs/__main__.py
qs/jobs.py
qs/misc.py
qs/proc.py
qs/qserve.py
qs/rpcclient.py
qs/rpcserver.py
qs/slave.py
qserve-0.3.1.dist-info/METADATA
qserve-0.3.1.dist-info/WHEEL
qserve-0.3.1.dist-info/top_level.txt
qserve-0.3.1.dist-info/RECORD
